looprint/__init__.py
looprint/looprint.py
looprint-0.1.0.dist-info/LICENSE
looprint-0.1.0.dist-info/METADATA
looprint-0.1.0.dist-info/WHEEL
looprint-0.1.0.dist-info/top_level.txt
looprint-0.1.0.dist-info/RECORD
