Metadata-Version: 2.1
Name: looprint
Version: 0.1.0
Summary: Simplify printing loops progress
Home-page: https://github.com/jonathanlombardo/terminal
Author: Jonathan Lombardo
Author-email: jonathanlombardo90@gmail.com
Classifier: Programming Language :: Python :: 3
Classifier: License :: OSI Approved :: MIT License
Classifier: Operating System :: OS Independent
Requires-Python: >=3.6
License-File: LICENSE
